README.md
setup.py
src/vdk/plugin/oracle/ingest_to_oracle.py
src/vdk/plugin/oracle/oracle_configuration.py
src/vdk/plugin/oracle/oracle_connection.py
src/vdk/plugin/oracle/oracle_plugin.py
src/vdk_oracle.egg-info/PKG-INFO
src/vdk_oracle.egg-info/SOURCES.txt
src/vdk_oracle.egg-info/dependency_links.txt
src/vdk_oracle.egg-info/entry_points.txt
src/vdk_oracle.egg-info/requires.txt
src/vdk_oracle.egg-info/top_level.txt
tests/test_plugin.py
tests/test_secrets_config.py