Metadata-Version: 2.1
Name: vdk-oracle
Version: 0.1.1147913641
Summary: Support for VDK Managed Oracle connection
Home-page: https://github.com/vmware/versatile-data-kit
Project-URL: Documentation, https://github.com/vmware/versatile-data-kit/tree/main/projects/vdk-plugins/vdk-oracle
Project-URL: Source Code, https://github.com/vmware/versatile-data-kit/tree/main/projects/vdk-plugins/vdk-oracle
Project-URL: Bug Tracker, https://github.com/vmware/versatile-data-kit/issues/new/choose
Classifier: Development Status :: 4 - Beta
Classifier: License :: OSI Approved :: Apache Software License
Classifier: Programming Language :: Python :: 3.7
Classifier: Programming Language :: Python :: 3.8
Classifier: Programming Language :: Python :: 3.9
Classifier: Programming Language :: Python :: 3.10
Classifier: Programming Language :: Python :: 3.11
Requires-Dist: vdk-core
Requires-Dist: oracledb
Requires-Dist: tabulate
